{
  "spark_version": "v4.0.0",
  "files_total": 303,
  "files_skipped": 63,
  "blocks_total": 12641,
  "strict_pass": 611,
  "semantic_pass": 5297,
  "buckets": {
    "correctness": 209,
    "datetime": 4,
    "decimal-precision": 137,
    "engine-panic": 1,
    "error-parity": 2463,
    "exec-error": 1031,
    "feature-unsupported": 405,
    "function-missing": 1340,
    "missing-error": 111,
    "missing-relation": 2726,
    "nondeterministic": 3,
    "null-semantics": 41,
    "ordering": 29,
    "parser-unsupported": 1336,
    "pass": 611,
    "schema-only": 2194
  }
}